tnng/__init__.py
tnng/generator.py
tnng/layer.py
tnng-0.4.1.dist-info/METADATA
tnng-0.4.1.dist-info/WHEEL
tnng-0.4.1.dist-info/top_level.txt
tnng-0.4.1.dist-info/RECORD
