Metadata-Version: 2.1
Name: tnng
Version: 0.4.1
Summary: Toy Neural Network Generator.
Home-page: https://github.com/0h-n0/toy_neural_network_generator
Author: Koji Ono
Author-email: koji.ono@exwzd.com
License: UNKNOWN
Platform: UNKNOWN
Classifier: Programming Language :: Python :: 3.6
Classifier: Programming Language :: Python :: 3.7
Classifier: Programming Language :: Python :: 3.8
Classifier: License :: OSI Approved :: MIT License
Requires-Python: >3.5
Requires-Dist: networkx (>=2.4)
Provides-Extra: docs
Requires-Dist: sphinx (>=1.4) ; extra == 'docs'
Requires-Dist: sphinx-rtd-theme ; extra == 'docs'
